[
    {
        "model": "peeldb.skill",
        "fields": {
            "name": "69",
            "status": "Active",
            "icon": ""
        }
    }, {
        "model": "peeldb.skill",
        "fields": {
            "name": "Adult Baby Minding",
            "status": "Active",
            "icon": ""
        }
    }, {
        "model": "peeldb.skill",
        "fields": {
            "name": "A Level - Anal",
            "status": "Active",
            "icon": ""
        }
    }, {
        "model": "peeldb.skill",
        "fields": {
            "name": "BDSM",
            "status": "Active",
            "icon": ""
        }
    }, {
        "model": "peeldb.skill",
        "fields": {
            "name": "Bisexual",
            "status": "Active",
            "icon": ""
        }
    }, {
        "model": "peeldb.skill",
        "fields": {
            "name": "Blowjob",
            "status": "Active",
            "icon": ""
        }
    }, {
        "model": "peeldb.skill",
        "fields": {
            "name": "Bukkake",
            "status": "Active",
            "icon": ""
        }
    }, {
        "model": "peeldb.skill",
        "fields": {
            "name": "Car Meets",
            "status": "Active",
            "icon": ""
        }
    }, {
        "model": "peeldb.skill",
        "fields": {
            "name": "CIF - Cum in Face",
            "status": "Active",
            "icon": ""
        }
    }, {
        "model": "peeldb.skill",
        "fields": {
            "name": "COB",
            "status": "Active",
            "icon": ""
        }
    }, {
        "model": "peeldb.skill",
        "fields": {
            "name": "Couples",
            "status": "Active",
            "icon": ""
        }
    }, {
        "model": "peeldb.skill",
        "fields": {
            "name": "Crossdresser",
            "status": "Active",
            "icon": ""
        }
    }, {
        "model": "peeldb.skill",
        "fields": {
            "name": "CIM - Cum in Mouth",
            "status": "Active",
            "icon": ""
        }
    }, {
        "model": "peeldb.skill",
        "fields": {
            "name": "Deep Throat",
            "status": "Active",
            "icon": ""
        }
    }, {
        "model": "peeldb.skill",
        "fields": {
            "name": "Dogging",
            "status": "Active",
            "icon": ""
        }
    }, {
        "model": "peeldb.skill",
        "fields": {
            "name": "Domination",
            "status": "Active",
            "icon": ""
        }
    }, {
        "model": "peeldb.skill",
        "fields": {
            "name": "DUO",
            "status": "Active",
            "icon": ""
        }
    }, {
        "model": "peeldb.skill",
        "fields": {
            "name": "Erotic massage",
            "status": "Active",
            "icon": ""
        }
    }, {
        "model": "peeldb.skill",
        "fields": {
            "name": "Face Sitting",
            "status": "Active",
            "icon": ""
        }
    }, {
        "model": "peeldb.skill",
        "fields": {
            "name": "Fetish",
            "status": "Active",
            "icon": ""
        }
    }, {
        "model": "peeldb.skill",
        "fields": {
            "name": "Filming",
            "status": "Active",
            "icon": ""
        }
    }, {
        "model": "peeldb.skill",
        "fields": {
            "name": "Fisting",
            "status": "Active",
            "icon": ""
        }
    }, {
        "model": "peeldb.skill",
        "fields": {
            "name": "French Kiss",
            "status": "Active",
            "icon": ""
        }
    }, {
        "model": "peeldb.skill",
        "fields": {
            "name": "Gang Bang",
            "status": "Active",
            "icon": ""
        }
    }, {
        "model": "peeldb.skill",
        "fields": {
            "name": "GFE",
            "status": "Active",
            "icon": ""
        }
    }, {
        "model": "peeldb.skill",
        "fields": {
            "name": "Hardcore sex",
            "status": "Active",
            "icon": ""
        }
    }, {
        "model": "peeldb.skill",
        "fields": {
            "name": "HDJ - Handjob",
            "status": "Active",
            "icon": ""
        }
    }, {
        "model": "peeldb.skill",
        "fields": {
            "name": "Incall",
            "status": "Active",
            "icon": ""
        }
    }, {
        "model": "peeldb.skill",
        "fields": {
            "name": "Kissing",
            "status": "Active",
            "icon": ""
        }
    }, {
        "model": "peeldb.skill",
        "fields": {
            "name": "Latex",
            "status": "Active",
            "icon": ""
        }
    }, {
        "model": "peeldb.skill",
        "fields": {
            "name": "Massage",
            "status": "Active",
            "icon": ""
        }
    }, {
        "model": "peeldb.skill",
        "fields": {
            "name": "Milking/Lactating",
            "status": "Active",
            "icon": ""
        }
    }, {
        "model": "peeldb.skill",
        "fields": {
            "name": "Outcall",
            "status": "Active",
            "icon": ""
        }
    }, {
        "model": "peeldb.skill",
        "fields": {
            "name": "OW",
            "status": "Active",
            "icon": ""
        }
    }, {
        "model": "peeldb.skill",
        "fields": {
            "name": "OWO",
            "status": "Active",
            "icon": ""
        }
    }, {
        "model": "peeldb.skill",
        "fields": {
            "name": "Party Girl",
            "status": "Active",
            "icon": ""
        }
    }, {
        "model": "peeldb.skill",
        "fields": {
            "name": "Pregnant",
            "status": "Active",
            "icon": ""
        }
    }, {
        "model": "peeldb.skill",
        "fields": {
            "name": "PSE - Pornstar",
            "status": "Active",
            "icon": ""
        }
    }, {
        "model": "peeldb.skill",
        "fields": {
            "name": "Quickie",
            "status": "Active",
            "icon": ""
        }
    }, {
        "model": "peeldb.skill",
        "fields": {
            "name": "Rimming",
            "status": "Active",
            "icon": ""
        }
    }, {
        "model": "peeldb.skill",
        "fields": {
            "name": "Rimming (giving)",
            "status": "Active",
            "icon": ""
        }
    }, {
        "model": "peeldb.skill",
        "fields": {
            "name": "Role-playing",
            "status": "Active",
            "icon": ""
        }
    }, {
        "model": "peeldb.skill",
        "fields": {
            "name": "Hardsports & Scat",
            "status": "Active",
            "icon": ""
        }
    }, {
        "model": "peeldb.skill",
        "fields": {
            "name": "Spanking",
            "status": "Active",
            "icon": ""
        }
    }, {
        "model": "peeldb.skill",
        "fields": {
            "name": "Sploshing",
            "status": "Active",
            "icon": ""
        }
    }, {
        "model": "peeldb.skill",
        "fields": {
            "name": "Squirting",
            "status": "Active",
            "icon": ""
        }
    }, {
        "model": "peeldb.skill",
        "fields": {
            "name": "Pegging - Strapon",
            "status": "Active",
            "icon": ""
        }
    }, {
        "model": "peeldb.skill",
        "fields": {
            "name": "Submissive",
            "status": "Active",
            "icon": ""
        }
    }, {
        "model": "peeldb.skill",
        "fields": {
            "name": "Swallow",
            "status": "Active",
            "icon": ""
        }
    }, {
        "model": "peeldb.skill",
        "fields": {
            "name": "Threesomes",
            "status": "Active",
            "icon": ""
        }
    }, {
        "model": "peeldb.skill",
        "fields": {
            "name": "Tie and Tease",
            "status": "Active",
            "icon": ""
        }
    }, {
        "model": "peeldb.skill",
        "fields": {
            "name": "Travel",
            "status": "Active",
            "icon": ""
        }
    }, {
        "model": "peeldb.skill",
        "fields": {
            "name": "Uniform",
            "status": "Active",
            "icon": ""
        }
    }
]